{
  "en": {
    "web_tools_title": "Web Tool Collection",
    "web_tools_subtitle": "Discover the most practical web tools to boost your productivity",
    "about_us": "About Us",
    "our_mission": "Our Mission",
    "contact_us": "Contact Us",
    "email": "Email",
    "github": "GitHub",
    "thanks_for_support": "Thank you for your support!",
    "comments": "Comments",
    "home_page": "Home Page",
    "search_tools": "Search tools...",
    "tool_categories": "Tool Categories",
    "all_tools": "All Tools",
    "new_feature": "New Feature!",
    "official": "Official",
    "original": "Original",
    "no_tools_found": "No relevant tools found",
    "go_to_tool": "Go to Tool",
    "back_to_home": "Back to Home",
    "loading": "Loading...",
    "category_image": "Image Processing",
    "category_text": "Text Processing",
    "category_converter": "Format Conversion",
    "category_interesting": "Creative Experience",
    "category_utility": "Utility Tools",
    "category_custom": "Original Tools"
  },
  "zh-CN": {
    "web_tools_title": "Web工具集",
    "web_tools_subtitle": "发现最实用的Web工具，提升您的工作效率",
    "about_us": "关于我们",
    "our_mission": "我们的使命",
    "contact_us": "联系我们",
    "email": "邮箱",
    "github": "GitHub",
    "thanks_for_support": "感谢您的支持！",
    "comments": "评论",
    "home_page": "主页",
    "search_tools": "搜索工具...",
    "tool_categories": "工具分类",
    "all_tools": "全部工具",
    "new_feature": "新功能！",
    "official": "官方",
    "original": "原创",
    "no_tools_found": "未找到相关工具",
    "go_to_tool": "前往工具",
    "back_to_home": "返回主页",
    "loading": "加载中...",
    "category_image": "图像处理",
    "category_text": "文本处理",
    "category_converter": "格式转换",
    "category_interesting": "创意体验",
    "category_utility": "实用工具",
    "category_custom": "原创工具"
  }
}
